pydoctordroid/__init__.py
pydoctordroid/_event_exporter.py
pydoctordroid/_events.py
pydoctordroid/_logger.py
pydoctordroid/_value.py
pydoctordroid/lib.py
drdroid_sdk-0.1.0.dist-info/LICENSE.txt
drdroid_sdk-0.1.0.dist-info/METADATA
drdroid_sdk-0.1.0.dist-info/WHEEL
drdroid_sdk-0.1.0.dist-info/top_level.txt
drdroid_sdk-0.1.0.dist-info/RECORD
